<?xml version="1.0" encoding="UTF-8"?>
<configuration>
    <!-- Console Appender for development -->
    <appender name="CONSOLE" class="ch.qos.logback.core.ConsoleAppender">
        <encoder>
            <pattern>%d{yyyy-MM-dd HH:mm:ss.SSS} [%thread] %-5level %logger{36} - %msg%n</pattern>
            <charset>UTF-8</charset>
        </encoder>
    </appender>

    <!-- Rolling File Appender for production -->
    <appender name="FILE" class="ch.qos.logback.core.rolling.RollingFileAppender">
        <file>logs/rakcha.log</file>
        <rollingPolicy class="ch.qos.logback.core.rolling.TimeBasedRollingPolicy">
            <!-- Daily rollover -->
            <fileNamePattern>logs/rakcha-%d{yyyy-MM-dd}.%i.log</fileNamePattern>
            <timeBasedFileNamingAndTriggeringPolicy class="ch.qos.logback.core.rolling.SizeAndTimeBasedFNATP">
                <!-- Max file size before rolling -->
                <maxFileSize>10MB</maxFileSize>
            </timeBasedFileNamingAndTriggeringPolicy>
            <!-- Keep 30 days of history -->
            <maxHistory>30</maxHistory>
            <!-- Total size of all archived logs -->
            <totalSizeCap>1GB</totalSizeCap>
        </rollingPolicy>
        <encoder>
            <pattern>%d{yyyy-MM-dd HH:mm:ss.SSS} [%thread] %-5level %logger{36} - %msg%n</pattern>
            <charset>UTF-8</charset>
        </encoder>
    </appender>

    <!-- Error File Appender -->
    <appender name="ERROR_FILE" class="ch.qos.logback.core.rolling.RollingFileAppender">
        <file>logs/rakcha-error.log</file>
        <filter class="ch.qos.logback.classic.filter.ThresholdFilter">
            <level>ERROR</level>
        </filter>
        <rollingPolicy class="ch.qos.logback.core.rolling.TimeBasedRollingPolicy">
            <fileNamePattern>logs/rakcha-error-%d{yyyy-MM-dd}.%i.log</fileNamePattern>
            <timeBasedFileNamingAndTriggeringPolicy class="ch.qos.logback.core.rolling.SizeAndTimeBasedFNATP">
                <maxFileSize>10MB</maxFileSize>
            </timeBasedFileNamingAndTriggeringPolicy>
            <maxHistory>90</maxHistory>
        </rollingPolicy>
        <encoder>
            <pattern>%d{yyyy-MM-dd HH:mm:ss.SSS} [%thread] %-5level %logger{36} - %msg%n</pattern>
            <charset>UTF-8</charset>
        </encoder>
    </appender>

    <!-- Audit Log Appender for security events -->
    <appender name="AUDIT_FILE" class="ch.qos.logback.core.rolling.RollingFileAppender">
        <file>logs/rakcha-audit.log</file>
        <rollingPolicy class="ch.qos.logback.core.rolling.TimeBasedRollingPolicy">
            <fileNamePattern>logs/rakcha-audit-%d{yyyy-MM-dd}.log</fileNamePattern>
            <maxHistory>365</maxHistory> <!-- Keep audit logs for 1 year -->
        </rollingPolicy>
        <encoder>
            <pattern>%d{yyyy-MM-dd HH:mm:ss.SSS} - %msg%n</pattern>
            <charset>UTF-8</charset>
        </encoder>
    </appender>

    <!-- Async wrapper for better performance -->
    <appender name="ASYNC_FILE" class="ch.qos.logback.classic.AsyncAppender">
        <appender-ref ref="FILE" />
        <queueSize>512</queueSize>
        <discardingThreshold>0</discardingThreshold>
    </appender>

    <!-- Package-specific loggers -->
    <logger name="com.esprit" level="DEBUG" additivity="false">
        <appender-ref ref="CONSOLE" />
        <appender-ref ref="ASYNC_FILE" />
        <appender-ref ref="ERROR_FILE" />
    </logger>

    <!-- Audit logger -->
    <logger name="com.esprit.security.AuditLogger" level="INFO" additivity="false">
        <appender-ref ref="AUDIT_FILE" />
    </logger>

    <!-- Third-party library loggers -->
    <logger name="org.hibernate" level="WARN" />
    <logger name="com.zaxxer.hikari" level="INFO" />
    <logger name="org.springframework" level="INFO" />
    <logger name="com.cloudinary" level="WARN" />
    <logger name="com.stripe" level="INFO" />

    <!-- SQL logging (set to DEBUG to see SQL queries) -->
    <logger name="org.hibernate.SQL" level="INFO" />
    <logger name="org.hibernate.type.descriptor.sql.BasicBinder" level="INFO" />

    <!-- Root logger -->
    <root level="INFO">
        <appender-ref ref="CONSOLE" />
        <appender-ref ref="ASYNC_FILE" />
        <appender-ref ref="ERROR_FILE" />
    </root>

    <!-- Shutdown hook to ensure logs are flushed -->
    <shutdownHook class="ch.qos.logback.core.hook.DelayingShutdownHook"/>
</configuration>
